sc_permut/__init__.py
sc_permut/__main__.py
sc_permut/analysis.py
sc_permut/api.py
sc_permut/clust_compute.py
sc_permut/dataset_utils.py
sc_permut/hyper.py
sc_permut/io.py
sc_permut/layers.py
sc_permut/load.py
sc_permut/loss.py
sc_permut/model.py
sc_permut/network.py
sc_permut/paths.py
sc_permut/permutation.py
sc_permut/predictor.py
sc_permut/run_dca_semi_sup.py
sc_permut/runfile_handler.py
sc_permut/test.py
sc_permut/train.py
sc_permut/utils.py
sc_permut/workflow.py
sc_permut-0.1.1.dist-info/LICENSE
sc_permut-0.1.1.dist-info/WHEEL
sc_permut-0.1.1.dist-info/METADATA
sc_permut-0.1.1.dist-info/entry_points.txt
sc_permut-0.1.1.dist-info/RECORD
