Metadata-Version: 2.1
Name: sc-permut
Version: 0.1.1
Summary: Deep learning annotation of cell-types with permutation inforced autoencoder
Home-page: https://sc_permut.readthedocs.io/
License: MIT
Author: becavin-lab
Requires-Python: >=3.7,<4.0
Classifier: License :: OSI Approved :: MIT License
Classifier: Programming Language :: Python :: 3
Classifier: Programming Language :: Python :: 3.7
Classifier: Programming Language :: Python :: 3.8
Classifier: Programming Language :: Python :: 3.9
Classifier: Programming Language :: Python :: 3.10
Classifier: Programming Language :: Python :: 3.11
Requires-Dist: keras (==2.4.3)
Requires-Dist: kopt (==0.1.0)
Requires-Dist: py4j (>=0.10.9.7,<0.11.0.0)
Requires-Dist: pyyaml (==5.3.1)
Requires-Dist: scanpy (==1.6.0)
Requires-Dist: tensorflow (==2.3.1)
Project-URL: Repository, https://github.com/becavin-lab/sc_permut/
